torchlensmaker/__init__.py
torchlensmaker/export_build123d.py
torchlensmaker/lenses.py
torchlensmaker/light_sources.py
torchlensmaker/materials.py
torchlensmaker/optical_data.py
torchlensmaker/optics.py
torchlensmaker/optimize.py
torchlensmaker/py.typed
torchlensmaker/analysis/colors.py
torchlensmaker/analysis/plot_magnification.py
torchlensmaker/analysis/plot_material_model.py
torchlensmaker/analysis/spot_diagram.py
torchlensmaker/core/collision_detection.py
torchlensmaker/core/full_forward.py
torchlensmaker/core/geometry.py
torchlensmaker/core/interp1d.py
torchlensmaker/core/intersect.py
torchlensmaker/core/outline.py
torchlensmaker/core/parameter.py
torchlensmaker/core/physics.py
torchlensmaker/core/rot2d.py
torchlensmaker/core/rot3d.py
torchlensmaker/core/sphere_sampling.py
torchlensmaker/core/surfaces.py
torchlensmaker/core/tensor_manip.py
torchlensmaker/core/tensorframe.py
torchlensmaker/core/transforms.py
torchlensmaker/sampling/__init__.py
torchlensmaker/sampling/samplers.py
torchlensmaker/testing/basic_transform.py
torchlensmaker/testing/check_local_collide.py
torchlensmaker/testing/collision_datasets.py
torchlensmaker/testing/dataset_view.py
torchlensmaker/viewer/py.typed
torchlensmaker/viewer/render_sequence.py
torchlensmaker/viewer/script_template.js
torchlensmaker/viewer/tlmviewer.py
torchlensmaker-0.0.10.dist-info/METADATA
torchlensmaker-0.0.10.dist-info/WHEEL
torchlensmaker-0.0.10.dist-info/licenses/LICENSE
torchlensmaker-0.0.10.dist-info/RECORD
