Metadata-Version: 2.4
Name: torchlensmaker
Version: 0.0.10
Summary: Differentiable geometric optics in PyTorch. Design optical systems with optimization.
Project-URL: Homepage, https://github.com/victorpoughon/torchlensmaker
Project-URL: Issues, https://github.com/victorpoughon/torchlensmaker/issues
Author-email: Victor Poughon <victor.poughon@gmail.com>
License:                     GNU GENERAL PUBLIC LICENSE
License-File: LICENSE
Classifier: Programming Language :: Python :: 3
Requires-Python: >=3.10
Requires-Dist: build123d~=0.9.1
Requires-Dist: colorcet>=3
Requires-Dist: matplotlib~=3.9.2
Requires-Dist: notebook>=7
Requires-Dist: torch~=2.4.1
Provides-Extra: test
Requires-Dist: nbmake~=1.5.4; extra == 'test'
Requires-Dist: nbstripout; extra == 'test'
Requires-Dist: nbstripout-fast; extra == 'test'
Requires-Dist: pytest~=8.3.3; extra == 'test'
